DIContainer.py
DIContainerInterface.py
paneric_di_container-1.0.0.dist-info/METADATA
paneric_di_container-1.0.0.dist-info/WHEEL
paneric_di_container-1.0.0.dist-info/top_level.txt
paneric_di_container-1.0.0.dist-info/RECORD
