Metadata-Version: 2.4
Name: paneric-di-container
Version: 1.0.0
Summary: A simple dependency injection container.
Home-page: https://gitlab.com/python5471645/libs/paneric-di-container
Author: Tomasz Januszewicz
Author-email: your.email@example.com
Dynamic: author
Dynamic: author-email
Dynamic: description
Dynamic: description-content-type
Dynamic: home-page
Dynamic: summary
